autodidaqt/__init__.py
autodidaqt/actor.py
autodidaqt/collections.py
autodidaqt/config.py
autodidaqt/core.py
autodidaqt/data.py
autodidaqt/examples/__init__.py
autodidaqt/examples/axis_settling.py
autodidaqt/examples/computed_axis.py
autodidaqt/examples/dataclass_binding.py
autodidaqt/examples/manual_axis.py
autodidaqt/examples/manuscript_fig4.py
autodidaqt/examples/minimal_app.py
autodidaqt/examples/plot_data.py
autodidaqt/examples/scanning_custom_plots.py
autodidaqt/examples/scanning_experiment.py
autodidaqt/examples/scanning_experiment_revisited.py
autodidaqt/examples/scanning_interlocks.py
autodidaqt/examples/scanning_properties_and_profiles.py
autodidaqt/examples/scanning_setup_and_teardown.py
autodidaqt/examples/scanning_time_to_completion.py
autodidaqt/examples/simple_actors.py
autodidaqt/examples/strategies.py
autodidaqt/examples/ui_panels.py
autodidaqt/examples/uninverted_control.py
autodidaqt/examples/wrapping_instruments.py
autodidaqt/experiment/__init__.py
autodidaqt/experiment/fsm.py
autodidaqt/experiment/run.py
autodidaqt/experiment/save.py
autodidaqt/globals.py
autodidaqt/instrument/__init__.py
autodidaqt/instrument/axis.py
autodidaqt/instrument/identify/__init__.py
autodidaqt/instrument/identify/lakeshore.py
autodidaqt/instrument/identify/newport.py
autodidaqt/instrument/identify/srs.py
autodidaqt/instrument/managed_instrument.py
autodidaqt/instrument/method.py
autodidaqt/instrument/property.py
autodidaqt/instrument/spec.py
autodidaqt/interlock.py
autodidaqt/mock.py
autodidaqt/notifications.py
autodidaqt/panel.py
autodidaqt/panels/__init__.py
autodidaqt/panels/basic_instrument_panel.py
autodidaqt/panels/experiment_panel.py
autodidaqt/panels/instrument_manager.py
autodidaqt/panels/log_panels.py
autodidaqt/reactive_utils/__init__.py
autodidaqt/registrar.py
autodidaqt/remote/__init__.py
autodidaqt/remote/link.py
autodidaqt/remote/scheduler.py
autodidaqt/resources/buttons.scss
autodidaqt/resources/default_config.json
autodidaqt-1.1.0.dist-info/LICENSE.txt
autodidaqt-1.1.0.dist-info/WHEEL
autodidaqt-1.1.0.dist-info/METADATA
autodidaqt-1.1.0.dist-info/RECORD
