Metadata-Version: 2.1
Name: autodidaqt
Version: 1.1.0
Summary: AutodiDAQt is a simple data acquisition framework. For science.
Home-page: https://github.com/chstan/autodidaqt-common
License: GNU GPL v3.0
Keywords: data acquisition,physics,instrumentation,DAQ
Author: chstan
Author-email: chstansbury@gmail.com
Requires-Python: >=3.8,<3.10
Classifier: Development Status :: 3 - Alpha
Classifier: Intended Audience :: Developers
Classifier: Intended Audience :: Science/Research
Classifier: License :: OSI Approved :: GNU General Public License v3 or later (GPLv3+)
Classifier: License :: Other/Proprietary License
Classifier: Natural Language :: English
Classifier: Operating System :: MacOS :: MacOS X
Classifier: Operating System :: Microsoft :: Windows :: Windows 10
Classifier: Operating System :: Microsoft :: Windows :: Windows 7
Classifier: Operating System :: Microsoft :: Windows :: Windows 8
Classifier: Operating System :: POSIX :: Linux
Classifier: Operating System :: Unix
Classifier: Programming Language :: Python
Classifier: Programming Language :: Python :: 3
Classifier: Programming Language :: Python :: 3.8
Classifier: Programming Language :: Python :: 3.9
Classifier: Programming Language :: Python :: Implementation :: CPython
Classifier: Topic :: Scientific/Engineering
Classifier: Topic :: Software Development :: Libraries :: Python Modules
Requires-Dist: PyQt5 (>=5.13.0,<5.14.0)
Requires-Dist: Quamash (>=0.6.1,<0.7.0)
Requires-Dist: appdirs (>=1.4.4,<1.5.0)
Requires-Dist: asyncqt (>=0.8.0,<0.9.0)
Requires-Dist: autodidaqt-common (>=0.1.0,<0.2.0)
Requires-Dist: dask (>=2021,<2022)
Requires-Dist: dataclasses_json (>=0.5.0,<0.6.0)
Requires-Dist: fsspec (>=2021,<2022)
Requires-Dist: instrumentkit (>=0.5,<0.6)
Requires-Dist: loguru (>=0.3.2,<0.4.0)
Requires-Dist: matplotlib (>=3.1.1,<4.0.0)
Requires-Dist: numpy (>=1.20,<2.0)
Requires-Dist: pandas (>=1.2.4,<2.0.0)
Requires-Dist: partd (>=1.2.0,<2.0.0)
Requires-Dist: pymeasure (>=0.9.0,<0.10.0)
Requires-Dist: pynng (>=0.7.1,<0.8.0)
Requires-Dist: pyqt-led (>=0.0.6,<0.1.0)
Requires-Dist: pyqtgraph (>=0.12.1,<0.13.0)
Requires-Dist: pyrsistent (>=0.17.3,<0.18.0)
Requires-Dist: python-dotenv (>=0.10.3,<0.11.0)
Requires-Dist: python-ivi (>=0.14.9,<0.15.0)
Requires-Dist: pyvisa (>=1.11.0,<2.0.0)
Requires-Dist: pyvisa-sim (>=0.4.0,<0.5.0)
Requires-Dist: qtsass (>=0.3.0,<0.4.0)
Requires-Dist: rx (>=3.0.1,<4.0.0)
Requires-Dist: scipy (>=1.7.0,<2.0.0)
Requires-Dist: slackclient (>=2.1.0,<3.0.0)
Requires-Dist: toolz (>=0.11.1,<0.12.0)
Requires-Dist: xarray (>=0.18.2,<0.19.0)
Requires-Dist: zarr (>=2.8.3,<3.0.0)
Project-URL: Repository, https://github.com/chstan/autodidaqt
